S3Upload/__init__.py
S3Upload/s3.py
meuprojetos3-1.2.1.dist-info/LICENSE.txt
meuprojetos3-1.2.1.dist-info/METADATA
meuprojetos3-1.2.1.dist-info/WHEEL
meuprojetos3-1.2.1.dist-info/top_level.txt
meuprojetos3-1.2.1.dist-info/RECORD
